cipher_sd3329/__init__.py
cipher_sd3329/cipher_sd3329.py
cipher_sd3329-0.1.0.dist-info/LICENSE
cipher_sd3329-0.1.0.dist-info/WHEEL
cipher_sd3329-0.1.0.dist-info/METADATA
cipher_sd3329-0.1.0.dist-info/RECORD
