Metadata-Version: 2.1
Name: cipher-sd3329
Version: 0.1.0
Summary: The package is used to encrypt or decrypt text via Caesar's cipher.
License: MIT
Author: Siyu
Author-email: sd3329@columbia.edu
Requires-Python: >=3.8,<4.0
Classifier: License :: OSI Approved :: MIT License
Classifier: Programming Language :: Python :: 3
Classifier: Programming Language :: Python :: 3.8
